MANIFEST.in
README.md
setup.py
bienes_inmuebles/__init__.py
bienes_inmuebles.egg-info/PKG-INFO
bienes_inmuebles.egg-info/SOURCES.txt
bienes_inmuebles.egg-info/dependency_links.txt
bienes_inmuebles.egg-info/requires.txt
bienes_inmuebles.egg-info/top_level.txt
bienes_inmuebles/base_datos/__init__.py
bienes_inmuebles/base_datos/metodosDb.py
bienes_inmuebles/formulario/__init__.py
bienes_inmuebles/formulario/metodosFormulario.py
bienes_inmuebles/formulario/objetoPrediccion.py
bienes_inmuebles/machine_learning/__init__.py
bienes_inmuebles/machine_learning/comprobacion_prediccion.py
bienes_inmuebles/machine_learning/main.py
bienes_inmuebles/machine_learning/modelos.py
bienes_inmuebles/machine_learning/no_supervisado.py
bienes_inmuebles/machine_learning/supervisado.py
bienes_inmuebles/preprocesar/__init__.py
bienes_inmuebles/preprocesar/csv_abrir.py
bienes_inmuebles/preprocesar/csv_exploracion.py
bienes_inmuebles/preprocesar/csv_plot.py
bienes_inmuebles/preprocesar/csv_preprocesamiento.py
bienes_inmuebles/preprocesar/main.py
bienes_inmuebles/recuperarDatos/__init__.py
bienes_inmuebles/recuperarDatos/fotocasa.py
bienes_inmuebles/recuperarDatos/inmueble.py
bienes_inmuebles/recuperarDatos/main.py
bienes_inmuebles/utilidades/__init__.py
bienes_inmuebles/utilidades/urlPath.py
docs/__init__.py
tests/__init__.py
tests/test_csv.py