Metadata-Version: 1.1
Name: bienes-inmuebles
Version: 1.1.1
Summary: Tool for predicitng real estate prices
Home-page: https://github.com/alexxfernandez13/bienes_inmuebles
Author: Alejandro Fernandez y Paco Leon
Author-email: alexxfernandez@hotmail.es
License: UNKNOWN
Platform: UNKNOWN
Classifier: Programming Language :: Python :: 3
Classifier: License :: OSI Approved :: MIT License
Classifier: Operating System :: OS Independent
